kickbotui
