Metadata-Version: 2.1
Name: kickbotui
Version: 0.0.6
Summary: Basic User-Interface for interacting with the kickbot package
Home-page: https://github.com/lukemvc/kickbotui
License: UNKNOWN
Platform: UNKNOWN
License-File: LICENSE
